[
  {
    "ContainingType": "MordidaCerta.WebAPI.Controllers.CategoriaController",
    "Method": "Get",
    "RelativePath": "api/Categoria",
    "HttpMethod": "GET",
    "IsController": true,
    "Order": 0,
    "Parameters": [],
    "ReturnTypes": []
  },
  {
    "ContainingType": "MordidaCerta.WebAPI.Controllers.CategoriaController",
    "Method": "Post",
    "RelativePath": "api/Categoria",
    "HttpMethod": "POST",
    "IsController": true,
    "Order": 0,
    "Parameters": [
      {
        "Name": "novaCategoria",
        "Type": "MordidaCerta.WebAPI.DTO.CategoriaDTO",
        "IsRequired": true
      }
    ],
    "ReturnTypes": []
  },
  {
    "ContainingType": "MordidaCerta.WebAPI.Controllers.CategoriaController",
    "Method": "PutBody",
    "RelativePath": "api/Categoria",
    "HttpMethod": "PUT",
    "IsController": true,
    "Order": 0,
    "Parameters": [
      {
        "Name": "categoriaAtualizada",
        "Type": "MordidaCerta.WebAPI.Models.Categoria",
        "IsRequired": true
      }
    ],
    "ReturnTypes": []
  },
  {
    "ContainingType": "MordidaCerta.WebAPI.Controllers.CategoriaController",
    "Method": "GetById",
    "RelativePath": "api/Categoria/{id}",
    "HttpMethod": "GET",
    "IsController": true,
    "Order": 0,
    "Parameters": [
      {
        "Name": "id",
        "Type": "System.Guid",
        "IsRequired": true
      }
    ],
    "ReturnTypes": []
  },
  {
    "ContainingType": "MordidaCerta.WebAPI.Controllers.CategoriaController",
    "Method": "Put",
    "RelativePath": "api/Categoria/{id}",
    "HttpMethod": "PUT",
    "IsController": true,
    "Order": 0,
    "Parameters": [
      {
        "Name": "id",
        "Type": "System.Guid",
        "IsRequired": true
      },
      {
        "Name": "categoriaAtualizada",
        "Type": "MordidaCerta.WebAPI.DTO.CategoriaDTO",
        "IsRequired": true
      }
    ],
    "ReturnTypes": []
  },
  {
    "ContainingType": "MordidaCerta.WebAPI.Controllers.ComidaController",
    "Method": "Get",
    "RelativePath": "api/Comida",
    "HttpMethod": "GET",
    "IsController": true,
    "Order": 0,
    "Parameters": [],
    "ReturnTypes": []
  },
  {
    "ContainingType": "MordidaCerta.WebAPI.Controllers.ComidaController",
    "Method": "Post",
    "RelativePath": "api/Comida",
    "HttpMethod": "POST",
    "IsController": true,
    "Order": 0,
    "Parameters": [
      {
        "Name": "Nome",
        "Type": "System.String",
        "IsRequired": false
      },
      {
        "Name": "Imagem",
        "Type": "Microsoft.AspNetCore.Http.IFormFile",
        "IsRequired": false
      },
      {
        "Name": "IdCategoria",
        "Type": "System.Nullable\u00601[[System.Guid, System.Private.CoreLib, Version=10.0.0.0, Culture=neutral, PublicKeyToken=7cec85d7bea7798e]]",
        "IsRequired": false
      }
    ],
    "ReturnTypes": []
  },
  {
    "ContainingType": "MordidaCerta.WebAPI.Controllers.ComidaController",
    "Method": "PutBody",
    "RelativePath": "api/Comida",
    "HttpMethod": "PUT",
    "IsController": true,
    "Order": 0,
    "Parameters": [
      {
        "Name": "comida",
        "Type": "MordidaCerta.WebAPI.Models.Comida",
        "IsRequired": true
      }
    ],
    "ReturnTypes": []
  },
  {
    "ContainingType": "MordidaCerta.WebAPI.Controllers.ComidaController",
    "Method": "GetById",
    "RelativePath": "api/Comida/{id}",
    "HttpMethod": "GET",
    "IsController": true,
    "Order": 0,
    "Parameters": [
      {
        "Name": "id",
        "Type": "System.Guid",
        "IsRequired": true
      }
    ],
    "ReturnTypes": []
  },
  {
    "ContainingType": "MordidaCerta.WebAPI.Controllers.ComidaController",
    "Method": "Put",
    "RelativePath": "api/Comida/{id}",
    "HttpMethod": "PUT",
    "IsController": true,
    "Order": 0,
    "Parameters": [
      {
        "Name": "id",
        "Type": "System.Guid",
        "IsRequired": true
      },
      {
        "Name": "Nome",
        "Type": "System.String",
        "IsRequired": false
      },
      {
        "Name": "Imagem",
        "Type": "Microsoft.AspNetCore.Http.IFormFile",
        "IsRequired": false
      },
      {
        "Name": "IdCategoria",
        "Type": "System.Nullable\u00601[[System.Guid, System.Private.CoreLib, Version=10.0.0.0, Culture=neutral, PublicKeyToken=7cec85d7bea7798e]]",
        "IsRequired": false
      }
    ],
    "ReturnTypes": []
  },
  {
    "ContainingType": "MordidaCerta.WebAPI.Controllers.ComidaController",
    "Method": "Delete",
    "RelativePath": "api/Comida/{id}",
    "HttpMethod": "DELETE",
    "IsController": true,
    "Order": 0,
    "Parameters": [
      {
        "Name": "id",
        "Type": "System.Guid",
        "IsRequired": true
      }
    ],
    "ReturnTypes": []
  },
  {
    "ContainingType": "MordidaCerta.WebAPI.Controllers.LoginController",
    "Method": "Login",
    "RelativePath": "api/Login",
    "HttpMethod": "POST",
    "IsController": true,
    "Order": 0,
    "Parameters": [
      {
        "Name": "loginDto",
        "Type": "MordidaCerta.WebAPI.DTO.LoginDTO",
        "IsRequired": true
      }
    ],
    "ReturnTypes": []
  },
  {
    "ContainingType": "MordidaCerta.WebAPI.Controllers.UsuarioController",
    "Method": "Post",
    "RelativePath": "api/Usuario",
    "HttpMethod": "POST",
    "IsController": true,
    "Order": 0,
    "Parameters": [
      {
        "Name": "novoUsuario",
        "Type": "MordidaCerta.WebAPI.DTO.UsuarioDTO",
        "IsRequired": true
      }
    ],
    "ReturnTypes": []
  }
]